qtawesome/__init__.py
qtawesome/_version.py
qtawesome/animation.py
qtawesome/icon_browser.py
qtawesome/iconic_font.py
qtawesome/styles.py
qtawesome/fonts/codicon-charmap.json
qtawesome/fonts/codicon.ttf
qtawesome/fonts/elusiveicons-webfont-charmap.json
qtawesome/fonts/elusiveicons-webfont.ttf
qtawesome/fonts/fontawesome4.7-webfont-charmap.json
qtawesome/fonts/fontawesome4.7-webfont.ttf
qtawesome/fonts/fontawesome5-brands-webfont-charmap.json
qtawesome/fonts/fontawesome5-brands-webfont.ttf
qtawesome/fonts/fontawesome5-regular-webfont-charmap.json
qtawesome/fonts/fontawesome5-regular-webfont.ttf
qtawesome/fonts/fontawesome5-solid-webfont-charmap.json
qtawesome/fonts/fontawesome5-solid-webfont.ttf
qtawesome/fonts/materialdesignicons5-webfont-charmap.json
qtawesome/fonts/materialdesignicons5-webfont.ttf
qtawesome/fonts/materialdesignicons6-webfont-charmap.json
qtawesome/fonts/materialdesignicons6-webfont.ttf
qtawesome/fonts/phosphor-charmap.json
qtawesome/fonts/phosphor.ttf
qtawesome/fonts/remixicon-charmap.json
qtawesome/fonts/remixicon.ttf
qtawesome/tests/test_icon_browser.py
qtawesome/tests/test_qtawesome.py
QtAwesome-1.3.0.dist-info/LICENSE.txt
QtAwesome-1.3.0.dist-info/METADATA
QtAwesome-1.3.0.dist-info/WHEEL
QtAwesome-1.3.0.dist-info/entry_points.txt
QtAwesome-1.3.0.dist-info/top_level.txt
QtAwesome-1.3.0.dist-info/RECORD
