Metadata-Version: 2.1
Name: QtAwesome
Version: 1.3.0
Summary: FontAwesome icons in PyQt and PySide applications
Home-page: https://github.com/spyder-ide/qtawesome
Author: Sylvain Corlay and the Spyder Development Team
Author-email: spyder.python@gmail.com
Maintainer: Spyder Development Team and QtAwesome Contributors
Maintainer-email: spyder.python@gmail.com
License: MIT
Keywords: PyQt,PySide,Icons,Font Awesome,Fonts
Platform: OS-independent
Classifier: Development Status :: 5 - Production/Stable
Classifier: Intended Audience :: Developers
Classifier: Topic :: Software Development :: User Interfaces
Classifier: License :: OSI Approved :: MIT License
Classifier: Programming Language :: Python :: 3
Classifier: Programming Language :: Python :: 3.7
Classifier: Programming Language :: Python :: 3.8
Classifier: Programming Language :: Python :: 3.9
Classifier: Programming Language :: Python :: 3.10
Requires-Python: >=3.7
License-File: LICENSE.txt
Requires-Dist: qtpy
